mcpf_io/io/__init__.py
mcpf_io-0.1.0.dist-info/LICENSE
mcpf_io-0.1.0.dist-info/METADATA
mcpf_io-0.1.0.dist-info/WHEEL
mcpf_io-0.1.0.dist-info/RECORD
